[
  {
    "address": "5E2LP6EnZ54m3wS8s1yPvD5c3xo71kQroBw7aUVK32TKeZ5u",
    "totalStake": "327453449206341",
    "ownStake": "140738424769870",
    "otherStake": "186715024436471",
    "minBond": "21000000",
    "nominatorCount": 26164,
    "commission": "0",
    "expectedReturn": "87.67",
    "blocked": false,
    "isVerified": false,
    "chain": "bittensor",
    "isCrowded": false,
    "identity": "tao.bot"
  },
  {
    "address": "5GKH9FPPnWSUoeeTJp19wVtd84XqFW4pyK2ijV2GsFbhTrP1",
    "totalStake": "248986582583955",
    "ownStake": "117239231726237",
    "otherStake": "131747350857718",
    "minBond": "21000000",
    "nominatorCount": 50122,
    "commission": "9",
    "expectedReturn": "70.31",
    "blocked": false,
    "isVerified": false,
    "chain": "bittensor",
    "isCrowded": false,
    "identity": "Taostats"
  },
  {
    "address": "5DXdHixxtCvoa6GHKs2Jgrdzc61882Ftx1zN2sYFQuwgL1S1",
    "totalStake": "176595292756560",
    "ownStake": "90356209031687",
    "otherStake": "86239083724873",
    "minBond": "21000000",
    "nominatorCount": 4930,
    "commission": "9",
    "expectedReturn": "76.99",
    "blocked": false,
    "isVerified": false,
    "chain": "bittensor",
    "isCrowded": false,
    "identity": "Yuma, a DCG Company"
  },
  {
    "address": "5G3wMP3g3d775hauwmAZioYFVZYnvw6eY46wkFy8hEWD5KP3",
    "totalStake": "161845867066129",
    "ownStake": "93877294951923",
    "otherStake": "67968572114206",
    "minBond": "21000000",
    "nominatorCount": 10292,
    "commission": "18",
    "expectedReturn": "71.89",
    "blocked": false,
    "isVerified": false,
    "chain": "bittensor",
    "isCrowded": false,
    "identity": "Openτensor Foundaτion"
  },
  {
    "address": "5Ckaoft1B1CQ9zBV2FLVju4KPuMQzJVn7QUf3JeTvTq1uUes",
    "totalStake": "122184553469628",
    "ownStake": "121627497971289",
    "otherStake": "557055498339",
    "minBond": "21000000",
    "nominatorCount": 270,
    "commission": "18",
    "expectedReturn": "0",
    "blocked": false,
    "isVerified": false,
    "chain": "bittensor",
    "isCrowded": false,
    "identity": "Kraken"
  },
  {
    "address": "5HK5tp6t2S59DywmHRWPBVJeJ86T61KjurYqeooqj8sREpeN",
    "totalStake": "115052782126010",
    "ownStake": "33838133627317",
    "otherStake": "81214648498693",
    "minBond": "21000000",
    "nominatorCount": 3999,
    "commission": "9",
    "expectedReturn": "79.78",
    "blocked": false,
    "isVerified": false,
    "chain": "bittensor",
    "isCrowded": false,
    "identity": "TAO.com"
  },
  {
    "address": "5Gq2gs4ft5dhhjbHabvVbAhjMCV2RgKmVJKAFCUWiirbRT21",
    "totalStake": "74195404660977",
    "ownStake": "59693091788368",
    "otherStake": "14502312872609",
    "minBond": "21000000",
    "nominatorCount": 5904,
    "commission": "9",
    "expectedReturn": "0",
    "blocked": false,
    "isVerified": false,
    "chain": "bittensor",
    "isCrowded": false,
    "identity": "RoundTable21"
  },
  {
    "address": "5HmkM6X1D3W3CuCSPuHhrbYyZNBy2aGAiZy9NczoJmtY25H7",
    "totalStake": "66033834643228",
    "ownStake": "51963249522859",
    "otherStake": "14070585120369",
    "minBond": "21000000",
    "nominatorCount": 1883,
    "commission": "9",
    "expectedReturn": "47.00",
    "blocked": false,
    "isVerified": false,
    "chain": "bittensor",
    "isCrowded": false,
    "identity": "Crucible Labs"
  },
  {
    "address": "5Dd8gaRNdhm1YP7G1hcB1N842ecAUQmbLjCRLqH5ycaTGrWv",
    "totalStake": "62529439974082",
    "ownStake": "52129130532802",
    "otherStake": "10400309441280",
    "minBond": "21000000",
    "nominatorCount": 204,
    "commission": "0",
    "expectedReturn": "87.67",
    "blocked": false,
    "isVerified": false,
    "chain": "bittensor",
    "isCrowded": false,
    "identity": "5Dd8gaRNdhm1YP7G1hcB1N842ecAUQmbLjCRLqH5ycaTGrWv"
  },
  {
    "address": "5CsvRJXuR955WojnGMdok1hbhffZyB4N5ocrv82f3p5A2zVp",
    "totalStake": "60717392984990",
    "ownStake": "40545815753976",
    "otherStake": "20171577231014",
    "minBond": "21000000",
    "nominatorCount": 5652,
    "commission": "9",
    "expectedReturn": "79.78",
    "blocked": false,
    "isVerified": false,
    "chain": "bittensor",
    "isCrowded": false,
    "identity": "tao5"
  },
  {
    "address": "5FxcZraZACr4L78jWkcYe3FHdiwiAUzrKLVtsSwkvFobBKqq",
    "totalStake": "56290011548472",
    "ownStake": "55126719781353",
    "otherStake": "1163291767119",
    "minBond": "21000000",
    "nominatorCount": 558,
    "commission": "18",
    "expectedReturn": "71.89",
    "blocked": false,
    "isVerified": false,
    "chain": "bittensor",
    "isCrowded": false,
    "identity": "Polychain"
  },
  {
    "address": "5GP7c3fFazW9GXK8Up3qgu2DJBk8inu4aK9TZy3RuoSWVCMi",
    "totalStake": "48839717542913",
    "ownStake": "13122699404554",
    "otherStake": "35717018138359",
    "minBond": "21000000",
    "nominatorCount": 4529,
    "commission": "0",
    "expectedReturn": "84.80",
    "blocked": false,
    "isVerified": false,
    "chain": "bittensor",
    "isCrowded": false,
    "identity": "Datura"
  },
  {
    "address": "5Dt7HZ7Zpw4DppPxFM7Ke3Cm7sDAWhsZXmM5ZAmE7dSVJbcQ",
    "totalStake": "46193046736320",
    "ownStake": "6032030500",
    "otherStake": "46187014705820",
    "minBond": "21000000",
    "nominatorCount": 3888,
    "commission": "0",
    "expectedReturn": "0",
    "blocked": false,
    "isVerified": false,
    "chain": "bittensor",
    "isCrowded": false,
    "identity": "Chutes / SN64 Primary Validator"
  },
  {
    "address": "5E4z3h9yVhmQyCFWNbY9BPpwhx4xFiPwq3eeqmBgVF6KULde",
    "totalStake": "40639178937675",
    "ownStake": "5750961618474",
    "otherStake": "34888217319201",
    "minBond": "21000000",
    "nominatorCount": 4318,
    "commission": "9",
    "expectedReturn": "79.78",
    "blocked": false,
    "isVerified": false,
    "chain": "bittensor",
    "isCrowded": false,
    "identity": "Tensorplex Labs"
  },
  {
    "address": "5FeNwZ5oAqcJMitNqGx71vxGRWJhsdTqxFGVwPRfg8h2UZmo",
    "totalStake": "35110013140616",
    "ownStake": "5850455064",
    "otherStake": "35104162685552",
    "minBond": "21000000",
    "nominatorCount": 143,
    "commission": "0",
    "expectedReturn": "0",
    "blocked": false,
    "isVerified": false,
    "chain": "bittensor",
    "isCrowded": false,
    "identity": "Glitch Financial"
  },
  {
    "address": "5FtBncJvGhxjBs4aFn2pid6aur9tBUuo9QR7sHe5DkoRizzo",
    "totalStake": "27649533145741",
    "ownStake": "17253469455367",
    "otherStake": "10396063690374",
    "minBond": "21000000",
    "nominatorCount": 2287,
    "commission": "9",
    "expectedReturn": "76.31",
    "blocked": false,
    "isVerified": false,
    "chain": "bittensor",
    "isCrowded": false,
    "identity": "Rizzo (Insured)"
  },
  {
    "address": "5DM7CPqPKtMSADhFKYsstsCS4Tm4Kd6PMXoh6DdqY4MtxmtX",
    "totalStake": "26376636757997",
    "ownStake": "2479898175853",
    "otherStake": "23896738582144",
    "minBond": "21000000",
    "nominatorCount": 2113,
    "commission": "0",
    "expectedReturn": "87.67",
    "blocked": false,
    "isVerified": false,
    "chain": "bittensor",
    "isCrowded": false,
    "identity": "Tαoscαn.io"
  },
  {
    "address": "5E4hBXkG9uVc1y9zdNzgCiLHrPbFukChkYeN1LxFnZgg4ASL",
    "totalStake": "23697656932122",
    "ownStake": "7756252226828",
    "otherStake": "15941404705294",
    "minBond": "21000000",
    "nominatorCount": 13754,
    "commission": "9",
    "expectedReturn": "78.92",
    "blocked": false,
    "isVerified": false,
    "chain": "bittensor",
    "isCrowded": false,
    "identity": "5E4hBXkG9uVc1y9zdNzgCiLHrPbFukChkYeN1LxFnZgg4ASL"
  },
  {
    "address": "5Hp18g9P8hLGKp9W3ZDr4bvJwba6b6bY3P2u3VdYf8yMR8FM",
    "totalStake": "23051830665104",
    "ownStake": "445397367",
    "otherStake": "23051385267737",
    "minBond": "21000000",
    "nominatorCount": 132,
    "commission": "18",
    "expectedReturn": "71.91",
    "blocked": false,
    "isVerified": false,
    "chain": "bittensor",
    "isCrowded": false,
    "identity": "5Hp18g9P8hLGKp9W3ZDr4bvJwba6b6bY3P2u3VdYf8yMR8FM"
  },
  {
    "address": "5Fy3MjrdKRvUWSuJa4Yd5dmBYunzKNmXnLcvP22NfaTvhQCY",
    "totalStake": "22310515344062",
    "ownStake": "12564238515699",
    "otherStake": "9746276828363",
    "minBond": "21000000",
    "nominatorCount": 3670,
    "commission": "9",
    "expectedReturn": "79.78",
    "blocked": false,
    "isVerified": false,
    "chain": "bittensor",
    "isCrowded": false,
    "identity": "Neuralteq.com"
  },
  {
    "address": "5G1NjW9YhXLadMWajvTkfcJy6up3yH2q1YzMXDTi6ijanChe",
    "totalStake": "20506232468363",
    "ownStake": "18524626213620",
    "otherStake": "1981606254743",
    "minBond": "21000000",
    "nominatorCount": 378,
    "commission": "18",
    "expectedReturn": "70.33",
    "blocked": false,
    "isVerified": false,
    "chain": "bittensor",
    "isCrowded": false,
    "identity": "5G1NjW9YhXLadMWajvTkfcJy6up3yH2q1YzMXDTi6ijanChe"
  },
  {
    "address": "5CVS9d1NcQyWKUyadLevwGxg6LgBcF9Lik6NSnbe5q59jwhE",
    "totalStake": "18807946590620",
    "ownStake": "5066568233117",
    "otherStake": "13741378357503",
    "minBond": "21000000",
    "nominatorCount": 2180,
    "commission": "0",
    "expectedReturn": "87.15",
    "blocked": false,
    "isVerified": false,
    "chain": "bittensor",
    "isCrowded": false,
    "identity": "Ary van der Touw"
  },
  {
    "address": "5G9hfkx9wGB1CLMT9WXkpHSAiYzjZb5o1Boyq4KAdDhjwrc5",
    "totalStake": "17134380725691",
    "ownStake": "4609808343147",
    "otherStake": "12524572382544",
    "minBond": "21000000",
    "nominatorCount": 2295,
    "commission": "0",
    "expectedReturn": "92.36",
    "blocked": false,
    "isVerified": false,
    "chain": "bittensor",
    "isCrowded": false,
    "identity": "1T1B.AI"
  },
  {
    "address": "5CoZxgtfhcJKX2HmkwnsN18KbaT9aih9eF3b6qVPTgAUbifj",
    "totalStake": "15913337122357",
    "ownStake": "4760916549096",
    "otherStake": "11152420573261",
    "minBond": "21000000",
    "nominatorCount": 2103,
    "commission": "18",
    "expectedReturn": "59.19",
    "blocked": false,
    "isVerified": false,
    "chain": "bittensor",
    "isCrowded": false,
    "identity": "TAO.app"
  },
  {
    "address": "5HjMs5JDrLH3Hknmfm1gDq7nFYAv6M7t9v3EWMctSRXJS9HC",
    "totalStake": "14132158807808",
    "ownStake": "1485210899",
    "otherStake": "14130673596909",
    "minBond": "21000000",
    "nominatorCount": 40,
    "commission": "18",
    "expectedReturn": "0",
    "blocked": false,
    "isVerified": false,
    "chain": "bittensor",
    "isCrowded": false,
    "identity": "Owner43"
  },
  {
    "address": "5GcAZ4SFfghRCYqhSTaeGqmgfosWfRRtSjp5T1YxpVuNHZCV",
    "totalStake": "13571558482952",
    "ownStake": "10865265486590",
    "otherStake": "2706292996362",
    "minBond": "21000000",
    "nominatorCount": 365,
    "commission": "0",
    "expectedReturn": "0",
    "blocked": false,
    "isVerified": false,
    "chain": "bittensor",
    "isCrowded": false,
    "identity": "xTAO"
  },
  {
    "address": "5EZ52JMq4S7PYqzmLAggYahyDirMx3p1f1uBtLQgx6fk7kR8",
    "totalStake": "13207975802657",
    "ownStake": "423",
    "otherStake": "13207975802234",
    "minBond": "21000000",
    "nominatorCount": 47,
    "commission": "5",
    "expectedReturn": "0",
    "blocked": false,
    "isVerified": false,
    "chain": "bittensor",
    "isCrowded": false,
    "identity": "qBitTensor Labs"
  },
  {
    "address": "5HdTZQ6UXD7MWcRsMeExVwqAKKo4UwomUd662HvtXiZXkxmv",
    "totalStake": "13134260853931",
    "ownStake": "14445450",
    "otherStake": "13134246408481",
    "minBond": "21000000",
    "nominatorCount": 185,
    "commission": "18",
    "expectedReturn": "0",
    "blocked": false,
    "isVerified": false,
    "chain": "bittensor",
    "isCrowded": false,
    "identity": "5HdTZQ6UXD7MWcRsMeExVwqAKKo4UwomUd662HvtXiZXkxmv"
  },
  {
    "address": "5DvTpiniW9s3APmHRYn8FroUWyfnLtrsid5Mtn5EwMXHN2ed",
    "totalStake": "12885326712478",
    "ownStake": "9998932979012",
    "otherStake": "2886393733466",
    "minBond": "21000000",
    "nominatorCount": 1283,
    "commission": "9",
    "expectedReturn": "79.78",
    "blocked": false,
    "isVerified": false,
    "chain": "bittensor",
    "isCrowded": false,
    "identity": "FirstTensor.com"
  },
  {
    "address": "5D4gEn5S422dTGR5NJJKZ93FNV6hDmfwDPfxFNgcoVnUkZ4f",
    "totalStake": "12692085179378",
    "ownStake": "9672882241368",
    "otherStake": "3019202938010",
    "minBond": "21000000",
    "nominatorCount": 2143,
    "commission": "7",
    "expectedReturn": "81.09",
    "blocked": false,
    "isVerified": false,
    "chain": "bittensor",
    "isCrowded": false,
    "identity": "Tatsu"
  },
  {
    "address": "5GgJptBaUiWwb8SQDinZ9rDQoVw47mgduXaCLHeJGTtA4JMS",
    "totalStake": "12415704969566",
    "ownStake": "967946724",
    "otherStake": "12414737022842",
    "minBond": "21000000",
    "nominatorCount": 225,
    "commission": "18",
    "expectedReturn": "0",
    "blocked": false,
    "isVerified": false,
    "chain": "bittensor",
    "isCrowded": false,
    "identity": "Ridges / SN62 Primary Validator"
  },
  {
    "address": "5CmKE9k1z1DDQBh81nfwRtbLq22mgS8wMPS9h36LVe4oGJTK",
    "totalStake": "11933244323406",
    "ownStake": "241214062",
    "otherStake": "11933003109344",
    "minBond": "21000000",
    "nominatorCount": 67,
    "commission": "18",
    "expectedReturn": "0",
    "blocked": false,
    "isVerified": false,
    "chain": "bittensor",
    "isCrowded": false,
    "identity": "Macrocosmos"
  },
  {
    "address": "5GxADSjVkV22Kbi7v4BTFsUzqTavrjkVNmf1zKq6FZLkYJ7H",
    "totalStake": "10340748710358",
    "ownStake": "617",
    "otherStake": "10340748709741",
    "minBond": "21000000",
    "nominatorCount": 83,
    "commission": "0",
    "expectedReturn": "0",
    "blocked": false,
    "isVerified": false,
    "chain": "bittensor",
    "isCrowded": false,
    "identity": "Sportstensor"
  },
  {
    "address": "5HbScNssaEfioJHXjcXdpyqo1AKnYjymidGF8opcF9rTFZdT",
    "totalStake": "10042304705879",
    "ownStake": "9401704983547",
    "otherStake": "640599722332",
    "minBond": "21000000",
    "nominatorCount": 357,
    "commission": "9",
    "expectedReturn": "79.78",
    "blocked": false,
    "isVerified": false,
    "chain": "bittensor",
    "isCrowded": false,
    "identity": "5HbScNssaEfioJHXjcXdpyqo1AKnYjymidGF8opcF9rTFZdT"
  },
  {
    "address": "5F2NCTUugqBHMPp5UyGjGMV9a94a2Eh6JDPBUFzWL2Zabjz8",
    "totalStake": "8660381332471",
    "ownStake": "3787448715463",
    "otherStake": "4872932617008",
    "minBond": "21000000",
    "nominatorCount": 5674,
    "commission": "9",
    "expectedReturn": "78.92",
    "blocked": false,
    "isVerified": false,
    "chain": "bittensor",
    "isCrowded": false,
    "identity": "5F2NCTUugqBHMPp5UyGjGMV9a94a2Eh6JDPBUFzWL2Zabjz8"
  },
  {
    "address": "5Gy7xTzDwXYw4JV1TUUUt28PwUTQ95HBCYFJMwkaDmnbQUJ5",
    "totalStake": "7563526401160",
    "ownStake": "180474622",
    "otherStake": "7563345926538",
    "minBond": "21000000",
    "nominatorCount": 92,
    "commission": "18",
    "expectedReturn": "0",
    "blocked": false,
    "isVerified": false,
    "chain": "bittensor",
    "isCrowded": false,
    "identity": "Synth"
  },
  {
    "address": "5FFM6Nvvm78GqyMratgXXvjbqZPi7SHgSQ81nyS96jBuUWgt",
    "totalStake": "7315770637925",
    "ownStake": "6419372353797",
    "otherStake": "896398284128",
    "minBond": "21000000",
    "nominatorCount": 385,
    "commission": "18",
    "expectedReturn": "71.41",
    "blocked": false,
    "isVerified": false,
    "chain": "bittensor",
    "isCrowded": false,
    "identity": "PRvalidator"
  },
  {
    "address": "5EZs9RgwoVAH7Gc1fWFpGcjSmJ9dDw8zjwgkKLgkTBUW6qXq",
    "totalStake": "6782576344491",
    "ownStake": "289",
    "otherStake": "6782576344202",
    "minBond": "21000000",
    "nominatorCount": 39,
    "commission": "18",
    "expectedReturn": "0",
    "blocked": false,
    "isVerified": false,
    "chain": "bittensor",
    "isCrowded": false,
    "identity": "5EZs9RgwoVAH7Gc1fWFpGcjSmJ9dDw8zjwgkKLgkTBUW6qXq"
  },
  {
    "address": "5Fq5v71D4LX8Db1xsmRSy6udQThcZ8sFDqxQFwnUZ1BuqY5A",
    "totalStake": "6758546577481",
    "ownStake": "5114798142056",
    "otherStake": "1643748435425",
    "minBond": "21000000",
    "nominatorCount": 386,
    "commission": "8",
    "expectedReturn": "0",
    "blocked": false,
    "isVerified": false,
    "chain": "bittensor",
    "isCrowded": false,
    "identity": "NorthTensor"
  },
  {
    "address": "5Deo9Q3SnZWNPSEPRTgapbyy6egKu2oaNSqD4RQHHJEuzD9Y",
    "totalStake": "6633780951531",
    "ownStake": "6562485438858",
    "otherStake": "71295512673",
    "minBond": "21000000",
    "nominatorCount": 438,
    "commission": "18",
    "expectedReturn": "71.89",
    "blocked": false,
    "isVerified": false,
    "chain": "bittensor",
    "isCrowded": false,
    "identity": "Firepool"
  },
  {
    "address": "5G1Qj93Fy22grpiGKq6BEvqqmS2HVRs3jaEdMhq9absQzs6g",
    "totalStake": "6237955993789",
    "ownStake": "570320032",
    "otherStake": "6237385673757",
    "minBond": "21000000",
    "nominatorCount": 241,
    "commission": "0",
    "expectedReturn": "0",
    "blocked": false,
    "isVerified": false,
    "chain": "bittensor",
    "isCrowded": false,
    "identity": "Hippius"
  },
  {
    "address": "5FFSBkNiymQWHaxc8dTmfTT7iHoz6YDexVG4xR2yLrffVR86",
    "totalStake": "5641442092658",
    "ownStake": "297440122967",
    "otherStake": "5344001969691",
    "minBond": "21000000",
    "nominatorCount": 208,
    "commission": "0",
    "expectedReturn": "0",
    "blocked": false,
    "isVerified": false,
    "chain": "bittensor",
    "isCrowded": false,
    "identity": "Kooltek68"
  },
  {
    "address": "5Dccjeya7SXuv5gAqYEzz3xMUkHAKvEY1obRET4U47uzf5oZ",
    "totalStake": "5173345685573",
    "ownStake": "232863013",
    "otherStake": "5173112822560",
    "minBond": "21000000",
    "nominatorCount": 69,
    "commission": "18",
    "expectedReturn": "0",
    "blocked": false,
    "isVerified": false,
    "chain": "bittensor",
    "isCrowded": false,
    "identity": "Tenexium.io"
  },
  {
    "address": "5F27Eqz2PhyMtGMEce898x31DokNqRVxkm5AhDDe6rDGNvoY",
    "totalStake": "5104240761811",
    "ownStake": "5009505588616",
    "otherStake": "94735173195",
    "minBond": "21000000",
    "nominatorCount": 110,
    "commission": "18",
    "expectedReturn": "0",
    "blocked": false,
    "isVerified": false,
    "chain": "bittensor",
    "isCrowded": false,
    "identity": "Love"
  },
  {
    "address": "5CszMVts9ueMUSKdAwLFSLT7u4oyxN7fUBpo8Z3ETw1ggMUV",
    "totalStake": "4610321757357",
    "ownStake": "2087892540009",
    "otherStake": "2522429217348",
    "minBond": "21000000",
    "nominatorCount": 555,
    "commission": "1",
    "expectedReturn": "83.37",
    "blocked": false,
    "isVerified": false,
    "chain": "bittensor",
    "isCrowded": false,
    "identity": "MUV"
  },
  {
    "address": "5Cf4LPRv6tiyuFsfLRQaFYEEn3zJRGi4bAE9DwbbKmbCSHpV",
    "totalStake": "4574931476487",
    "ownStake": "877882759",
    "otherStake": "4574053593728",
    "minBond": "21000000",
    "nominatorCount": 47,
    "commission": "18",
    "expectedReturn": "0",
    "blocked": false,
    "isVerified": false,
    "chain": "bittensor",
    "isCrowded": false,
    "identity": "Owner14"
  },
  {
    "address": "5CPH55YWSFX38mBZ6jeUo86Me7VP347kcisBNMpTgAU42FBr",
    "totalStake": "4117419141249",
    "ownStake": "393",
    "otherStake": "4117419140856",
    "minBond": "21000000",
    "nominatorCount": 18,
    "commission": "18",
    "expectedReturn": "0",
    "blocked": false,
    "isVerified": false,
    "chain": "bittensor",
    "isCrowded": false,
    "identity": "5CPH55YWSFX38mBZ6jeUo86Me7VP347kcisBNMpTgAU42FBr"
  },
  {
    "address": "5DnNzmms8Pg7YekmHsDjJXKUMYeBG8ziM9nMj19pfiH5vs45",
    "totalStake": "4098327477663",
    "ownStake": "10291434669",
    "otherStake": "4088036042994",
    "minBond": "21000000",
    "nominatorCount": 102,
    "commission": "18",
    "expectedReturn": "0",
    "blocked": false,
    "isVerified": false,
    "chain": "bittensor",
    "isCrowded": false,
    "identity": "Rizzo (Insured)"
  },
  {
    "address": "5F9uEDDovurwEJihzZSpKypipVy84EEAPHTt3EfepTjcQfij",
    "totalStake": "3733117252186",
    "ownStake": "15760551504",
    "otherStake": "3717356700682",
    "minBond": "21000000",
    "nominatorCount": 77,
    "commission": "18",
    "expectedReturn": "0",
    "blocked": false,
    "isVerified": false,
    "chain": "bittensor",
    "isCrowded": false,
    "identity": "grail"
  },
  {
    "address": "5E7eSeRr2aHzCV7SkY4a2Pi5NXHrU4anZz3phEQgn4HCen2B",
    "totalStake": "3554955388381",
    "ownStake": "18021650",
    "otherStake": "3554937366731",
    "minBond": "21000000",
    "nominatorCount": 11,
    "commission": "18",
    "expectedReturn": "0",
    "blocked": false,
    "isVerified": false,
    "chain": "bittensor",
    "isCrowded": false,
    "identity": "Owner17"
  },
  {
    "address": "5G3qVaXzKMPDm5AJ3dpzbpUC27kpccBvDwzSWXrq8M6qMmbC",
    "totalStake": "3425858681134",
    "ownStake": "4749",
    "otherStake": "3425858676385",
    "minBond": "21000000",
    "nominatorCount": 42,
    "commission": "18",
    "expectedReturn": "0",
    "blocked": false,
    "isVerified": false,
    "chain": "bittensor",
    "isCrowded": false,
    "identity": "basilica"
  },
  {
    "address": "5Dnkprjf9fUrvWq3ZfFP8WrUNSjQws6UoHkbDfR1bQK8pFhW",
    "totalStake": "3355558428117",
    "ownStake": "127638",
    "otherStake": "3355558300479",
    "minBond": "21000000",
    "nominatorCount": 32,
    "commission": "18",
    "expectedReturn": "0",
    "blocked": false,
    "isVerified": false,
    "chain": "bittensor",
    "isCrowded": false,
    "identity": "fx-integral"
  },
  {
    "address": "5CGLCBndTR1BvQZzn429ckT8GyxduzyjMgt4K1UVTYa8gKfb",
    "totalStake": "3129767172225",
    "ownStake": "35238",
    "otherStake": "3129767136987",
    "minBond": "21000000",
    "nominatorCount": 59,
    "commission": "18",
    "expectedReturn": "0",
    "blocked": false,
    "isVerified": false,
    "chain": "bittensor",
    "isCrowded": false,
    "identity": "Macrocosmos"
  },
  {
    "address": "5D5GWNQ2hw9tDdBkgPTg5PiBKbjZTCNFiAKmVKbhgshXsn6o",
    "totalStake": "2796345236528",
    "ownStake": "5770758014",
    "otherStake": "2790574478514",
    "minBond": "21000000",
    "nominatorCount": 94,
    "commission": "18",
    "expectedReturn": "0",
    "blocked": false,
    "isVerified": false,
    "chain": "bittensor",
    "isCrowded": false,
    "identity": "RoundTable21"
  },
  {
    "address": "5CdNo8k6UQgW9mGAmEKUGU5MTvazvF96q75KMMJbbCqBsn46",
    "totalStake": "2733650042201",
    "ownStake": "8",
    "otherStake": "2733650042193",
    "minBond": "21000000",
    "nominatorCount": 101,
    "commission": "18",
    "expectedReturn": "0",
    "blocked": false,
    "isVerified": false,
    "chain": "bittensor",
    "isCrowded": false,
    "identity": "RoundTable21"
  },
  {
    "address": "5FyUNRQ26cvNwCPGobiNiabcVsRksczDE8mKxHvQSebNEBcD",
    "totalStake": "2586929389067",
    "ownStake": "8157273",
    "otherStake": "2586921231794",
    "minBond": "21000000",
    "nominatorCount": 482,
    "commission": "18",
    "expectedReturn": "56.87",
    "blocked": false,
    "isVerified": false,
    "chain": "bittensor",
    "isCrowded": false,
    "identity": "TaoFi Validator"
  },
  {
    "address": "5HB4fHsv49fibXiY59j3TW8oSZAZmju6AiuMvCowL9E35jVw",
    "totalStake": "2568228361994",
    "ownStake": "4126",
    "otherStake": "2568228357868",
    "minBond": "21000000",
    "nominatorCount": 19,
    "commission": "18",
    "expectedReturn": "0",
    "blocked": false,
    "isVerified": false,
    "chain": "bittensor",
    "isCrowded": false,
    "identity": "AgentBuilder"
  },
  {
    "address": "5HBg742kVS1KXhKQGJhEMsyNcxatQzpyttipazfqGJSBS98o",
    "totalStake": "2499477309055",
    "ownStake": "295",
    "otherStake": "2499477308760",
    "minBond": "21000000",
    "nominatorCount": 19,
    "commission": "18",
    "expectedReturn": "0",
    "blocked": false,
    "isVerified": false,
    "chain": "bittensor",
    "isCrowded": false,
    "identity": "InfiniteHash Chef"
  },
  {
    "address": "5FYwKoHYfiuy9m2yM4wbwM5pQyaEP38MBTTZS8RwNKRuQ8mi",
    "totalStake": "2472681579333",
    "ownStake": "1213",
    "otherStake": "2472681578120",
    "minBond": "21000000",
    "nominatorCount": 45,
    "commission": "18",
    "expectedReturn": "0",
    "blocked": false,
    "isVerified": false,
    "chain": "bittensor",
    "isCrowded": false,
    "identity": "Macrocosmos"
  },
  {
    "address": "5CaEd14Wjz6h6Yy4Z74GSa2sdPjUm1oNsdrxX7sXz1HPsn63",
    "totalStake": "2343697549137",
    "ownStake": "2549663",
    "otherStake": "2343694999474",
    "minBond": "21000000",
    "nominatorCount": 121,
    "commission": "18",
    "expectedReturn": "0",
    "blocked": false,
    "isVerified": false,
    "chain": "bittensor",
    "isCrowded": false,
    "identity": "RoundTable21"
  },
  {
    "address": "5HTn5NcpCMabvHysyESrNirifM4GQqQJSnBT64kM7qCBas64",
    "totalStake": "2314291955021",
    "ownStake": "394788789",
    "otherStake": "2313897166232",
    "minBond": "21000000",
    "nominatorCount": 374,
    "commission": "18",
    "expectedReturn": "0",
    "blocked": false,
    "isVerified": false,
    "chain": "bittensor",
    "isCrowded": false,
    "identity": "Rizzo (Insured)"
  },
  {
    "address": "5GTAcDHetmSqBqUSUW6fUCY2LkV1uKZqyVg8dKA4Va6NpNH5",
    "totalStake": "2232628265388",
    "ownStake": "1105691630",
    "otherStake": "2231522573758",
    "minBond": "21000000",
    "nominatorCount": 35,
    "commission": "18",
    "expectedReturn": "0",
    "blocked": false,
    "isVerified": false,
    "chain": "bittensor",
    "isCrowded": false,
    "identity": "Nickel5"
  },
  {
    "address": "5GU4Xkd3dCGTU3s8VLcHGc5wsD5M8XyxDca5yDQhYm1mVXFu",
    "totalStake": "2228988771390",
    "ownStake": "12345971960",
    "otherStake": "2216642799430",
    "minBond": "21000000",
    "nominatorCount": 30,
    "commission": "18",
    "expectedReturn": "0",
    "blocked": false,
    "isVerified": false,
    "chain": "bittensor",
    "isCrowded": false,
    "identity": "Owner56"
  },
  {
    "address": "5DtBXSbZH3GV4Mv6JiT5JGasQDMh66hdm3VHy4PNq1rQWVtP",
    "totalStake": "2205567820857",
    "ownStake": "144845",
    "otherStake": "2205567676012",
    "minBond": "21000000",
    "nominatorCount": 15,
    "commission": "18",
    "expectedReturn": "0",
    "blocked": false,
    "isVerified": false,
    "chain": "bittensor",
    "isCrowded": false,
    "identity": "5DtBXSbZH3GV4Mv6JiT5JGasQDMh66hdm3VHy4PNq1rQWVtP"
  },
  {
    "address": "5GQyFzvtVMw9X45t6dvUFgR9unFpDCccPPCiAoqJrtPuC8my",
    "totalStake": "2158565028594",
    "ownStake": "866128",
    "otherStake": "2158564162466",
    "minBond": "21000000",
    "nominatorCount": 30,
    "commission": "18",
    "expectedReturn": "0",
    "blocked": false,
    "isVerified": false,
    "chain": "bittensor",
    "isCrowded": false,
    "identity": "ReadyAI Validator"
  },
  {
    "address": "5GmvyePN9aYErXBBhBnxZKGoGk4LKZApE4NkaSzW62CYCYNA",
    "totalStake": "1976346868537",
    "ownStake": "1610115975601",
    "otherStake": "366230892936",
    "minBond": "21000000",
    "nominatorCount": 444,
    "commission": "9",
    "expectedReturn": "0",
    "blocked": false,
    "isVerified": false,
    "chain": "bittensor",
    "isCrowded": false,
    "identity": "Neural Internet"
  },
  {
    "address": "5D7aRtpmVBKsQRzMA2ioUPL25onJPzBjiFVVt5uPZ3TDsn51",
    "totalStake": "1893310880494",
    "ownStake": "2434",
    "otherStake": "1893310878060",
    "minBond": "21000000",
    "nominatorCount": 285,
    "commission": "18",
    "expectedReturn": "0",
    "blocked": false,
    "isVerified": false,
    "chain": "bittensor",
    "isCrowded": false,
    "identity": "RoundTable21"
  },
  {
    "address": "5Eho9y6iF5aTdKS28Awn2pKTd4dFsJ2o3shGtj1vjnLiaKJ1",
    "totalStake": "1874151412551",
    "ownStake": "2",
    "otherStake": "1874151412549",
    "minBond": "21000000",
    "nominatorCount": 76,
    "commission": "9",
    "expectedReturn": "0",
    "blocked": false,
    "isVerified": false,
    "chain": "bittensor",
    "isCrowded": false,
    "identity": "Yuma, a DCG Company"
  },
  {
    "address": "5DUmbxsTWuMxefEk36BYX8qNsF18BbUeTgBPuefBN6gSDe8j",
    "totalStake": "1866072920539",
    "ownStake": "629",
    "otherStake": "1866072919910",
    "minBond": "21000000",
    "nominatorCount": 30,
    "commission": "18",
    "expectedReturn": "0",
    "blocked": false,
    "isVerified": false,
    "chain": "bittensor",
    "isCrowded": false,
    "identity": "Web Agents - Autoppia"
  },
  {
    "address": "5E1nK3myeWNWrmffVaH76f2mCFCbe9VcHGwgkfdcD7k3E8D1",
    "totalStake": "1852606888915",
    "ownStake": "1",
    "otherStake": "1852606888914",
    "minBond": "21000000",
    "nominatorCount": 36,
    "commission": "18",
    "expectedReturn": "0",
    "blocked": false,
    "isVerified": false,
    "chain": "bittensor",
    "isCrowded": false,
    "identity": "5E1nK3myeWNWrmffVaH76f2mCFCbe9VcHGwgkfdcD7k3E8D1"
  },
  {
    "address": "5GHrTeuFnJYjNJx773URbYb9Pk3bRRDiJHJFBNECZpjGqZPY",
    "totalStake": "1520401944699",
    "ownStake": "2554",
    "otherStake": "1520401942145",
    "minBond": "21000000",
    "nominatorCount": 89,
    "commission": "18",
    "expectedReturn": "0",
    "blocked": false,
    "isVerified": false,
    "chain": "bittensor",
    "isCrowded": false,
    "identity": "TAO Private Network"
  },
  {
    "address": "5DUB7kNLvvx8Dj7D8tn54N1C7Xok6GodNPQE2WECCaL9Wgpr",
    "totalStake": "1496478889286",
    "ownStake": "6565115574",
    "otherStake": "1489913773712",
    "minBond": "21000000",
    "nominatorCount": 39,
    "commission": "0",
    "expectedReturn": "0",
    "blocked": false,
    "isVerified": false,
    "chain": "bittensor",
    "isCrowded": false,
    "identity": "Yanez MIID"
  },
  {
    "address": "5EWwdZB7qCCMaAso5Mzcks4UUcPxKYvpAj32t5Mg1v6HSxoF",
    "totalStake": "1490245122787",
    "ownStake": "99748261",
    "otherStake": "1490145374526",
    "minBond": "21000000",
    "nominatorCount": 10,
    "commission": "18",
    "expectedReturn": "0",
    "blocked": false,
    "isVerified": false,
    "chain": "bittensor",
    "isCrowded": false,
    "identity": "5EWwdZB7qCCMaAso5Mzcks4UUcPxKYvpAj32t5Mg1v6HSxoF"
  },
  {
    "address": "5DCNqfcoAPBrb2htSqftp51tsM3dMzmod8tB6bES3ipzCQLm",
    "totalStake": "1488836702666",
    "ownStake": "1170345551",
    "otherStake": "1487666357115",
    "minBond": "21000000",
    "nominatorCount": 50,
    "commission": "18",
    "expectedReturn": "0",
    "blocked": false,
    "isVerified": false,
    "chain": "bittensor",
    "isCrowded": false,
    "identity": "5DCNqfcoAPBrb2htSqftp51tsM3dMzmod8tB6bES3ipzCQLm"
  },
  {
    "address": "5CFxLBvpyQq3TCP7zLcu8dLcPBxhA6MdLvXiCyvJVojuK17J",
    "totalStake": "1481217863265",
    "ownStake": "3",
    "otherStake": "1481217863262",
    "minBond": "21000000",
    "nominatorCount": 16,
    "commission": "18",
    "expectedReturn": "0",
    "blocked": false,
    "isVerified": false,
    "chain": "bittensor",
    "isCrowded": false,
    "identity": "Owner2"
  },
  {
    "address": "5GeEtY7Ars1FbSKhueoffzLHrYgw3rxn7eF6egicCbWmNs71",
    "totalStake": "1471840444156",
    "ownStake": "6746",
    "otherStake": "1471840437410",
    "minBond": "21000000",
    "nominatorCount": 48,
    "commission": "18",
    "expectedReturn": "0",
    "blocked": false,
    "isVerified": false,
    "chain": "bittensor",
    "isCrowded": false,
    "identity": "Rizzo (Insured)"
  },
  {
    "address": "5Ci3icAs5c9vMUFkjT1nDqfD8N8hXEFkgfe161aT7AYB1s5o",
    "totalStake": "1326288049181",
    "ownStake": "20171036871",
    "otherStake": "1306117012310",
    "minBond": "21000000",
    "nominatorCount": 85,
    "commission": "18",
    "expectedReturn": "0",
    "blocked": false,
    "isVerified": false,
    "chain": "bittensor",
    "isCrowded": false,
    "identity": "Rizzo (Insured)"
  },
  {
    "address": "5HK4vbGgLQdFKarN3hLVqNRbgQtQR5w3WTZ2tTnFHHLPgXpY",
    "totalStake": "1312320679166",
    "ownStake": "110",
    "otherStake": "1312320679056",
    "minBond": "21000000",
    "nominatorCount": 47,
    "commission": "18",
    "expectedReturn": "0",
    "blocked": false,
    "isVerified": false,
    "chain": "bittensor",
    "isCrowded": false,
    "identity": "88"
  },
  {
    "address": "5CAAxTpdKUAkQ28aYAPABGXxSGpAkQ6u8jQPwmg5mMaKpQ1C",
    "totalStake": "1257916555486",
    "ownStake": "1603573",
    "otherStake": "1257914951913",
    "minBond": "21000000",
    "nominatorCount": 213,
    "commission": "9",
    "expectedReturn": "0",
    "blocked": false,
    "isVerified": false,
    "chain": "bittensor",
    "isCrowded": false,
    "identity": "Yuma, a DCG Company"
  },
  {
    "address": "5CUaVirdkxdTnMDJWGwqbhSXYUogULj9WUneqnXV4Wc5RwWJ",
    "totalStake": "1200797674481",
    "ownStake": "88",
    "otherStake": "1200797674393",
    "minBond": "21000000",
    "nominatorCount": 23,
    "commission": "18",
    "expectedReturn": "0",
    "blocked": false,
    "isVerified": false,
    "chain": "bittensor",
    "isCrowded": false,
    "identity": "Macrocosmos"
  },
  {
    "address": "5FR392L6eKrTGwUjQurpxw89YUe7LzKANktDwRKLYYSgwxhb",
    "totalStake": "1198362158641",
    "ownStake": "20",
    "otherStake": "1198362158621",
    "minBond": "21000000",
    "nominatorCount": 42,
    "commission": "18",
    "expectedReturn": "0",
    "blocked": false,
    "isVerified": false,
    "chain": "bittensor",
    "isCrowded": false,
    "identity": "Vidaio"
  },
  {
    "address": "5C515Vu4AesgMjdUekVJqsxdJLP2x7oRjR2ouVVSuFXDsn56",
    "totalStake": "1115113611788",
    "ownStake": "21344040645",
    "otherStake": "1093769571143",
    "minBond": "21000000",
    "nominatorCount": 454,
    "commission": "18",
    "expectedReturn": "0",
    "blocked": false,
    "isVerified": false,
    "chain": "bittensor",
    "isCrowded": false,
    "identity": "RoundTable21"
  },
  {
    "address": "5CDnZ6oeCrXKoL2VJQuQFxSfr49yQWz2DvdaYx47hr9QdM6D",
    "totalStake": "1046753297190",
    "ownStake": "8",
    "otherStake": "1046753297182",
    "minBond": "21000000",
    "nominatorCount": 10,
    "commission": "18",
    "expectedReturn": "0",
    "blocked": false,
    "isVerified": false,
    "chain": "bittensor",
    "isCrowded": false,
    "identity": "Owner46"
  },
  {
    "address": "5ELREhApbCahM7FyGLM1V9WDsnnjCRmMCJTmtQD51oAEqwVh",
    "totalStake": "1011736907608",
    "ownStake": "367994864297",
    "otherStake": "643742043311",
    "minBond": "21000000",
    "nominatorCount": 333,
    "commission": "9",
    "expectedReturn": "79.58",
    "blocked": false,
    "isVerified": false,
    "chain": "bittensor",
    "isCrowded": false,
    "identity": "Taofu Protocol"
  },
  {
    "address": "5GuRsre3hqm6WKWRCqVxXdM4UtGs457nDhPo9F5wvJ16Ys62",
    "totalStake": "965268551501",
    "ownStake": "621",
    "otherStake": "965268550880",
    "minBond": "21000000",
    "nominatorCount": 82,
    "commission": "18",
    "expectedReturn": "0",
    "blocked": false,
    "isVerified": false,
    "chain": "bittensor",
    "isCrowded": false,
    "identity": "Rizzo (Insured)"
  },
  {
    "address": "5CX7hJX4Mduham7CRy9UkCM2V2ngw5b1xknKyX8Cwsttr2VN",
    "totalStake": "939670991592",
    "ownStake": "2397600000",
    "otherStake": "937273391592",
    "minBond": "21000000",
    "nominatorCount": 41,
    "commission": "18",
    "expectedReturn": "0",
    "blocked": false,
    "isVerified": false,
    "chain": "bittensor",
    "isCrowded": false,
    "identity": "Openτensor Foundaτion"
  },
  {
    "address": "5FWiXLaW5s9q8xC7FrBZ3JkGJyC6Feh2Xep5awRWrJPesMpz",
    "totalStake": "929905760428",
    "ownStake": "3225577738",
    "otherStake": "926680182690",
    "minBond": "21000000",
    "nominatorCount": 23,
    "commission": "18",
    "expectedReturn": "0",
    "blocked": false,
    "isVerified": false,
    "chain": "bittensor",
    "isCrowded": false,
    "identity": "Chutes / SN128 Primary Validator"
  },
  {
    "address": "5FZ1BFw8eRMAFK5zwJdyefrsn51Lrm217WKbo3MmdFH65YRr",
    "totalStake": "903588504685",
    "ownStake": "5981089521",
    "otherStake": "897607415164",
    "minBond": "21000000",
    "nominatorCount": 72,
    "commission": "18",
    "expectedReturn": "0",
    "blocked": false,
    "isVerified": false,
    "chain": "bittensor",
    "isCrowded": false,
    "identity": "Openτensor Foundaτion"
  },
  {
    "address": "5Cahv5hiySF25r7upSZUcwgM6LPsyVf1LN2puB7vkMgGsn74",
    "totalStake": "856444824283",
    "ownStake": "429",
    "otherStake": "856444823854",
    "minBond": "21000000",
    "nominatorCount": 29,
    "commission": "18",
    "expectedReturn": "0",
    "blocked": false,
    "isVerified": false,
    "chain": "bittensor",
    "isCrowded": false,
    "identity": "RoundTable21"
  },
  {
    "address": "5CK49hDJcseEk1V7iB1dmmztdw4igafhxLsVN82VtUVAQRfC",
    "totalStake": "852694199267",
    "ownStake": "8782699",
    "otherStake": "852685416568",
    "minBond": "21000000",
    "nominatorCount": 28,
    "commission": "18",
    "expectedReturn": "0",
    "blocked": false,
    "isVerified": false,
    "chain": "bittensor",
    "isCrowded": false,
    "identity": "Owner19"
  },
  {
    "address": "5F4Q3cA8EvApwhBj4eLjbb1meiLtzKgWhkF5JLRMNhRfqULc",
    "totalStake": "783341391309",
    "ownStake": "1009620227",
    "otherStake": "782331771082",
    "minBond": "21000000",
    "nominatorCount": 57,
    "commission": "18",
    "expectedReturn": "0",
    "blocked": false,
    "isVerified": false,
    "chain": "bittensor",
    "isCrowded": false,
    "identity": "Owner64"
  },
  {
    "address": "5EXXUEhZmqG9fzyURV6YfqEEAHK1gwrKpfVD57iHgq7Wss68",
    "totalStake": "728856763007",
    "ownStake": "197945680941",
    "otherStake": "530911082066",
    "minBond": "21000000",
    "nominatorCount": 164,
    "commission": "18",
    "expectedReturn": "0",
    "blocked": false,
    "isVerified": false,
    "chain": "bittensor",
    "isCrowded": false,
    "identity": "Rizzo (Insured)"
  },
  {
    "address": "5CrSrEdM36RyLaSzTnRCJUvG7kAEJWjdvAd5S5APATVRsn47",
    "totalStake": "724296129274",
    "ownStake": "44",
    "otherStake": "724296129230",
    "minBond": "21000000",
    "nominatorCount": 44,
    "commission": "18",
    "expectedReturn": "0",
    "blocked": false,
    "isVerified": false,
    "chain": "bittensor",
    "isCrowded": false,
    "identity": "RoundTable21"
  },
  {
    "address": "5EnC86fRRRoaXUZvkrDFYpAihuyEAp3wGkY5r3Gak1kPTDVP",
    "totalStake": "683046046748",
    "ownStake": "1",
    "otherStake": "683046046747",
    "minBond": "21000000",
    "nominatorCount": 32,
    "commission": "18",
    "expectedReturn": "0",
    "blocked": false,
    "isVerified": false,
    "chain": "bittensor",
    "isCrowded": false,
    "identity": "Distributed Training"
  },
  {
    "address": "5FZe9Mpo5dLXfhGZ4VjRnw6dmz9LVPp6nzqPyDfaS9BLKs33",
    "totalStake": "623247610822",
    "ownStake": "10982",
    "otherStake": "623247599840",
    "minBond": "21000000",
    "nominatorCount": 56,
    "commission": "18",
    "expectedReturn": "0",
    "blocked": false,
    "isVerified": false,
    "chain": "bittensor",
    "isCrowded": false,
    "identity": "Rizzo (Insured)"
  },
  {
    "address": "5CmJzrj2vVGnpYHWoKRMRkntsgRJjzfFmbgZMXu4Rg2wEs41",
    "totalStake": "617009192658",
    "ownStake": "12402",
    "otherStake": "617009180256",
    "minBond": "21000000",
    "nominatorCount": 87,
    "commission": "18",
    "expectedReturn": "0",
    "blocked": false,
    "isVerified": false,
    "chain": "bittensor",
    "isCrowded": false,
    "identity": "Rizzo (Insured)"
  },
  {
    "address": "5CaUzefiAdnjvyREwA2nnxjHLwvTLurNrBsUWkTVUZoJsn98",
    "totalStake": "599234006620",
    "ownStake": "4114757973",
    "otherStake": "595119248647",
    "minBond": "21000000",
    "nominatorCount": 22,
    "commission": "18",
    "expectedReturn": "0",
    "blocked": false,
    "isVerified": false,
    "chain": "bittensor",
    "isCrowded": false,
    "identity": "RoundTable21"
  },
  {
    "address": "5EAMc5c16J9dfdNuds29Ke4edwDYnevAwKz5stBvULjVzFB5",
    "totalStake": "530413748565",
    "ownStake": "1984616756",
    "otherStake": "528429131809",
    "minBond": "21000000",
    "nominatorCount": 16,
    "commission": "18",
    "expectedReturn": "0",
    "blocked": false,
    "isVerified": false,
    "chain": "bittensor",
    "isCrowded": false,
    "identity": "DogeLayer"
  },
  {
    "address": "5FpsgU3JFa8S2GnngH92J9vtHHi4PYgZzxGXnwdFNwEwt9h8",
    "totalStake": "523701983727",
    "ownStake": "2228570043",
    "otherStake": "521473413684",
    "minBond": "21000000",
    "nominatorCount": 13,
    "commission": "18",
    "expectedReturn": "0",
    "blocked": false,
    "isVerified": false,
    "chain": "bittensor",
    "isCrowded": false,
    "identity": "Owner128"
  },
  {
    "address": "5GzjAcUcD3pFk5ybJ1qP4tMfnyk2Kh3SX8R2kMQwPU2dTs63",
    "totalStake": "519882748654",
    "ownStake": "8977",
    "otherStake": "519882739677",
    "minBond": "21000000",
    "nominatorCount": 34,
    "commission": "18",
    "expectedReturn": "0",
    "blocked": false,
    "isVerified": false,
    "chain": "bittensor",
    "isCrowded": false,
    "identity": "Rizzo (Insured)"
  },
  {
    "address": "5CfNstXqRDxtgs6uU2pcCvwGu3iRm9rU799R616mQgpyQsn7",
    "totalStake": "515186365743",
    "ownStake": "5441789",
    "otherStake": "515180923954",
    "minBond": "21000000",
    "nominatorCount": 70,
    "commission": "18",
    "expectedReturn": "0",
    "blocked": false,
    "isVerified": false,
    "chain": "bittensor",
    "isCrowded": false,
    "identity": "RoundTable21"
  },
  {
    "address": "5C8V32baxQx7gAh1Tewcpot8hnG2WkGhC87JG3wZgCMsDsn5",
    "totalStake": "500356225920",
    "ownStake": "649",
    "otherStake": "500356225271",
    "minBond": "21000000",
    "nominatorCount": 154,
    "commission": "18",
    "expectedReturn": "0",
    "blocked": false,
    "isVerified": false,
    "chain": "bittensor",
    "isCrowded": false,
    "identity": "RoundTable21"
  },
  {
    "address": "5FFFjWqpNcu2yweMNaYcya5bq6zRuAAWJsudCyN462nLKhtj",
    "totalStake": "412117751653",
    "ownStake": "900074825",
    "otherStake": "411217676828",
    "minBond": "21000000",
    "nominatorCount": 14,
    "commission": "0",
    "expectedReturn": "0",
    "blocked": false,
    "isVerified": false,
    "chain": "bittensor",
    "isCrowded": false,
    "identity": "TaoLend"
  },
  {
    "address": "5G1G2kJPomq9xJttsfvX3XchywHvS1o2qUFCoUkPo5ShZs18",
    "totalStake": "381876529156",
    "ownStake": "3115427584",
    "otherStake": "378761101572",
    "minBond": "21000000",
    "nominatorCount": 66,
    "commission": "18",
    "expectedReturn": "0",
    "blocked": false,
    "isVerified": false,
    "chain": "bittensor",
    "isCrowded": false,
    "identity": "Rizzo (Insured)"
  },
  {
    "address": "5FsGZaVPH785MPRPQobkMuYkHmCKSkZkFp9aamjCbKdyRZQC",
    "totalStake": "374106835961",
    "ownStake": "366686411265",
    "otherStake": "7420424696",
    "minBond": "21000000",
    "nominatorCount": 62,
    "commission": "9",
    "expectedReturn": "0",
    "blocked": false,
    "isVerified": false,
    "chain": "bittensor",
    "isCrowded": false,
    "identity": "5FsGZaVPH785MPRPQobkMuYkHmCKSkZkFp9aamjCbKdyRZQC"
  },
  {
    "address": "5E4eKP81Pe2YG99QqMNpGgEUJDcHRcoxmwGZ5D9dfrrTRcc1",
    "totalStake": "370116344132",
    "ownStake": "2450784928",
    "otherStake": "367665559204",
    "minBond": "21000000",
    "nominatorCount": 54,
    "commission": "18",
    "expectedReturn": "0",
    "blocked": false,
    "isVerified": false,
    "chain": "bittensor",
    "isCrowded": false,
    "identity": "MMO.AI"
  }
]